{"images":[{"height":485,"width":561,"id":1,"file_name":"created_image_2022_06_23 16:47:17.745499.jpg"}],"annotations":[{"iscrowd":0,"image_id":1,"bbox":[245,438,18,24],"segmentation":[],"category_id":8,"id":1,"area":432},{"iscrowd":0,"image_id":1,"bbox":[223,438,19,24],"segmentation":[],"category_id":3,"id":2,"area":456},{"iscrowd":0,"image_id":1,"bbox":[204,438,17,24],"segmentation":[],"category_id":9,"id":3,"area":408},{"iscrowd":0,"image_id":1,"bbox":[182,438,17,24],"segmentation":[],"category_id":21,"id":4,"area":408},{"iscrowd":0,"image_id":1,"bbox":[159,438,18,24],"segmentation":[],"category_id":2,"id":5,"area":432},{"iscrowd":0,"image_id":1,"bbox":[150,438,3,24],"segmentation":[],"category_id":18,"id":6,"area":72},{"iscrowd":0,"image_id":1,"bbox":[125,438,19,26],"segmentation":[],"category_id":35,"id":7,"area":494},{"iscrowd":0,"image_id":1,"bbox":[102,438,17,24],"segmentation":[],"category_id":12,"id":8,"area":408},{"iscrowd":0,"image_id":1,"bbox":[78,438,17,24],"segmentation":[],"category_id":23,"id":9,"area":408},{"iscrowd":0,"image_id":1,"bbox":[54,438,19,24],"segmentation":[],"category_id":13,"id":10,"area":456},{"iscrowd":0,"image_id":1,"bbox":[32,438,18,24],"segmentation":[],"category_id":32,"id":11,"area":432}],"categories":[{"id":0,"name":"0","supercategory":"0"},{"id":1,"name":"1","supercategory":"1"},{"id":2,"name":"2","supercategory":"2"},{"id":3,"name":"3","supercategory":"3"},{"id":4,"name":"4","supercategory":"4"},{"id":5,"name":"5","supercategory":"5"},{"id":6,"name":"6","supercategory":"6"},{"id":7,"name":"7","supercategory":"7"},{"id":8,"name":"8","supercategory":"8"},{"id":9,"name":"9","supercategory":"9"},{"id":10,"name":"A","supercategory":"A"},{"id":11,"name":"B","supercategory":"B"},{"id":12,"name":"C","supercategory":"C"},{"id":13,"name":"D","supercategory":"D"},{"id":14,"name":"E","supercategory":"E"},{"id":15,"name":"F","supercategory":"F"},{"id":16,"name":"G","supercategory":"G"},{"id":17,"name":"H","supercategory":"H"},{"id":18,"name":"I","supercategory":"I"},{"id":19,"name":"J","supercategory":"J"},{"id":20,"name":"K","supercategory":"K"},{"id":21,"name":"L","supercategory":"L"},{"id":22,"name":"M","supercategory":"M"},{"id":23,"name":"N","supercategory":"N"},{"id":24,"name":"O","supercategory":"O"},{"id":25,"name":"P","supercategory":"P"},{"id":26,"name":"Q","supercategory":"Q"},{"id":27,"name":"R","supercategory":"R"},{"id":28,"name":"S","supercategory":"S"},{"id":29,"name":"T","supercategory":"T"},{"id":30,"name":"U","supercategory":"U"},{"id":31,"name":"V","supercategory":"V"},{"id":32,"name":"W","supercategory":"W"},{"id":33,"name":"X","supercategory":"X"},{"id":34,"name":"Y","supercategory":"Y"},{"id":35,"name":"Z","supercategory":"Z"}]}